setup.py
datastore/__init__.py
datastore.aws.egg-info/PKG-INFO
datastore.aws.egg-info/SOURCES.txt
datastore.aws.egg-info/dependency_links.txt
datastore.aws.egg-info/namespace_packages.txt
datastore.aws.egg-info/requires.txt
datastore.aws.egg-info/top_level.txt
datastore/aws/__init__.py
datastore/aws/test.py