Metadata-Version: 1.0
Name: datastore.aws
Version: 0.1.2
Summary: aws datastore implementation
Home-page: http://github.com/datastore/datastore.aws
Author: Juan Batiz-Benet
Author-email: juan@benet.ai
License: MIT License
Keywords: datastore,aws,s3
Platform: UNKNOWN
Classifier: Topic :: Database
Classifier: Topic :: Database :: Front-Ends
